{
  "collectionName": "components_services_heroes",
  "info": {
    "displayName": "Hero",
    "icon": "bold",
    "description": ""
  },
  "options": {},
  "attributes": {
    "lead": {
      "type": "string",
      "required": true
    },
    "title": {
      "type": "string",
      "required": true
    },
    "description": {
      "type": "text",
      "required": true
    },
    "buttons": {
      "displayName": "buttons",
      "type": "component",
      "repeatable": true,
      "component": "common.buttons"
    }
  }
}
