{
  "kind": "singleType",
  "collectionName": "accomodations",
  "info": {
    "singularName": "accomodation",
    "pluralName": "accomodations",
    "displayName": "Accomodation",
    "description": ""
  },
  "options": {
    "draftAndPublish": true
  },
  "pluginOptions": {},
  "attributes": {
    "subtitle": {
      "type": "string"
    },
    "title": {
      "type": "string",
      "required": true
    },
    "description": {
      "type": "richtext"
    },
    "facilities": {
      "displayName": "Facility",
      "type": "component",
      "repeatable": true,
      "component": "common.facility"
    },
    "mainImages": {
      "type": "media",
      "multiple": true,
      "required": true,
      "allowedTypes": [
        "images"
      ]
    },
    "otherImages": {
      "type": "media",
      "multiple": true,
      "required": false,
      "allowedTypes": [
        "images"
      ]
    },
    "subtitle2": {
      "type": "string"
    },
    "title2": {
      "type": "string"
    },
    "description2": {
      "type": "richtext"
    },
    "facilities2": {
      "type": "component",
      "repeatable": true,
      "component": "common.facility"
    },
    "mainImages2": {
      "type": "media",
      "multiple": true,
      "required": false,
      "allowedTypes": [
        "images"
      ]
    },
    "facilities_title": {
      "type": "string"
    },
    "facilities_title2": {
      "type": "string"
    }
  }
}
